{
    "geode": "2.0.0-beta.22",
    "gd": {
        "android": "2.205",
        "win": "2.204"
    },
    "version": "v1.0.2",
    "id": "hiimjustin000.better_icon_randomizer",
    "name": "Better Icon Randomizer",
    "developer": "hiimjustin000",
    "description": "Adds a button to randomize the current icon mode or color, and one to randomize all. (Unlocked icons and colors only)",
    "repository": "https://github.com/hiimjustin000/BetterIconRandomizer",
    "dependencies": [
        {
            "id": "geode.node-ids",
            "version": ">=v1.8.1",
            "importance": "required"
        }
    ],
    "resources": {
        "sprites": [
            "resources/*.png"
        ]
    }
}